_bleio-stubs/__init__.pyi
_eve-stubs/__init__.pyi
_pew-stubs/__init__.pyi
_pixelmap-stubs/__init__.pyi
_stage-stubs/__init__.pyi
adafruit_bus_device-stubs/__init__.pyi
adafruit_bus_device-stubs/i2c_device/__init__.pyi
adafruit_bus_device-stubs/spi_device/__init__.pyi
adafruit_pixelbuf-stubs/__init__.pyi
aesio-stubs/__init__.pyi
alarm-stubs/__init__.pyi
alarm-stubs/pin/__init__.pyi
alarm-stubs/time/__init__.pyi
alarm-stubs/touch/__init__.pyi
analogbufio-stubs/__init__.pyi
analogio-stubs/__init__.pyi
atexit-stubs/__init__.pyi
audiobusio-stubs/__init__.pyi
audiocore-stubs/__init__.pyi
audiodelays-stubs/__init__.pyi
audiofilters-stubs/__init__.pyi
audiofreeverb-stubs/__init__.pyi
audioio-stubs/__init__.pyi
audiomixer-stubs/__init__.pyi
audiomp3-stubs/__init__.pyi
audiopwmio-stubs/__init__.pyi
aurora_epaper-stubs/__init__.pyi
bitbangio-stubs/__init__.pyi
bitmapfilter-stubs/__init__.pyi
bitmaptools-stubs/__init__.pyi
bitops-stubs/__init__.pyi
board-stubs/__init__.pyi
board_definitions/01space_lcd042_esp32c3/__init__.pyi
board_definitions/0xcb_gemini/__init__.pyi
board_definitions/0xcb_helios/__init__.pyi
board_definitions/42keebs_frood/__init__.pyi
board_definitions/8086_commander/__init__.pyi
board_definitions/8086_rp2040_interfacer/__init__.pyi
board_definitions/8086_usb_interposer/__init__.pyi
board_definitions/ADM_B_NRF52840_1/__init__.pyi
board_definitions/Seeed_XIAO_nRF52840_Sense/__init__.pyi
board_definitions/TG-Watch/__init__.pyi
board_definitions/adafruit_esp32s3_camera/__init__.pyi
board_definitions/adafruit_feather_esp32_v2/__init__.pyi
board_definitions/adafruit_feather_esp32c6_4mbflash_nopsram/__init__.pyi
board_definitions/adafruit_feather_esp32s2/__init__.pyi
board_definitions/adafruit_feather_esp32s2_reverse_tft/__init__.pyi
board_definitions/adafruit_feather_esp32s2_tft/__init__.pyi
board_definitions/adafruit_feather_esp32s3_4mbflash_2mbpsram/__init__.pyi
board_definitions/adafruit_feather_esp32s3_nopsram/__init__.pyi
circuitpython_stubs-10.0.3.dist-info/METADATA
circuitpython_stubs-10.0.3.dist-info/WHEEL
circuitpython_stubs-10.0.3.dist-info/entry_points.txt
circuitpython_stubs-10.0.3.dist-info/top_level.txt
circuitpython_stubs-10.0.3.dist-info/RECORD
