Metadata-Version: 2.4
Name: circuitpython-stubs
Version: 10.0.3
Summary: PEP 561 type stubs for CircuitPython
Home-page: https://github.com/adafruit/circuitpython
Author-email: circuitpython@adafruit.com
Maintainer: CircuitPythonistas
Maintainer-email: circuitpython@adafruit.com
License: MIT
Dynamic: author-email
Dynamic: home-page
Dynamic: license
Dynamic: maintainer
Dynamic: maintainer-email
Dynamic: summary
